{
  "ok": true,
  "state": "熊市消化",
  "trend": "趋势空",
  "funding": "资金防守",
  "risk_level": "LOW",
  "confidence": 0.6812038005615804,
  "validation": {
    "risk_thermometer": "高烧威胁",
    "ath_drawdown": 44.605620641251384,
    "ath_price": 124797.86,
    "etf_accelerator": "顺风",
    "etf_net_flow": 117500000.0,
    "etf_aum": 80097930488.0,
    "etf_flow_14d_sum": 217900000.0,
    "etf_flow_pos_ratio": 0.6,
    "etf_flow_recent_avg": -15628571.42857143,
    "etf_flow_prev_avg": 46757142.85714286,
    "etf_flow_trend": "down",
    "etf_aum_trend": "up"
  },
  "metadata": {
    "btc_price": 69131.0,
    "ma50": 68699.3882,
    "ma200": 90399.41925,
    "ma50_slope": -0.07558268519414213,
    "ma200_slope": -0.24687870446770122,
    "total_market_cap": 2454954221037.925,
    "stablecoin_market_cap": 267571863292.11658,
    "stablecoin_ratio": 10.899260808985286,
    "stablecoin_change": 22640672659.246307,
    "stablecoin_ratio_change": 2.899260808985286,
    "stablecoin_ratio_gap": null,
    "stablecoin_slope": -0.5518313466142954,
    "total_slope": -0.5518313466142954,
    "ath_drawdown": 44.605620641251384
  }
}