{
  "ok": true,
  "state": "熊市反弹",
  "trend": "趋势空",
  "funding": "资金进攻",
  "risk_level": "MEDIUM",
  "confidence": 0.46937687949707807,
  "validation": {
    "risk_thermometer": "高烧威胁",
    "ath_drawdown": 35.23767154340627,
    "ath_price": 124797.86,
    "etf_accelerator": "顺风",
    "etf_net_flow": 27200000.0,
    "etf_aum": 96257768848.0,
    "etf_flow_14d_sum": 1395100000.0,
    "etf_flow_pos_ratio": 0.7,
    "etf_flow_recent_avg": 184085714.2857143,
    "etf_flow_prev_avg": 15214285.714285715,
    "etf_flow_trend": "up",
    "etf_aum_trend": "up"
  },
  "metadata": {
    "btc_price": 80822.0,
    "ma50": 74404.17540000001,
    "ma200": 82483.5438,
    "ma50_slope": 0.2682312013948973,
    "ma200_slope": -0.16646392658684617,
    "total_market_cap": 2778504221103.7095,
    "stablecoin_market_cap": 273771536310.4414,
    "stablecoin_ratio": 9.853198502671006,
    "stablecoin_change": 22062777231.70804,
    "stablecoin_ratio_change": 1.853198502671006,
    "stablecoin_ratio_gap": null,
    "stablecoin_slope": 0.2907586873856838,
    "total_slope": 0.2907586873856838,
    "ath_drawdown": 35.23767154340627
  }
}