{
  "ok": true,
  "state": "熊市反弹",
  "trend": "趋势空",
  "funding": "资金进攻",
  "risk_level": "MEDIUM",
  "confidence": 0.6924069916586557,
  "validation": {
    "risk_thermometer": "高烧威胁",
    "ath_drawdown": 45.25066375336885,
    "ath_price": 124797.86,
    "etf_accelerator": "钝化",
    "etf_net_flow": -41100000.0,
    "etf_aum": 80097930488.0,
    "etf_flow_14d_sum": 1347800000.0,
    "etf_flow_pos_ratio": 0.43333333333333335,
    "etf_flow_recent_avg": 157600000.0,
    "etf_flow_prev_avg": 34942857.14285714,
    "etf_flow_trend": "up",
    "etf_aum_trend": "up"
  },
  "metadata": {
    "btc_price": 68326.0,
    "ma50": 74798.9504,
    "ma200": 95718.37074999999,
    "ma50_slope": -0.6286948467981168,
    "ma200_slope": -0.2554265812075296,
    "total_market_cap": 2411057298462.112,
    "stablecoin_market_cap": 267109268919.16742,
    "stablecoin_ratio": 11.078511866538491,
    "stablecoin_change": 42747832982.362,
    "stablecoin_ratio_change": 3.0785118665384914,
    "stablecoin_ratio_gap": null,
    "stablecoin_slope": 0.5663178549429215,
    "total_slope": 0.5663178549429215,
    "ath_drawdown": 45.25066375336885
  }
}