{
  "ok": true,
  "state": "熊市反弹",
  "trend": "趋势空",
  "funding": "资金进攻",
  "risk_level": "MEDIUM",
  "confidence": 0.6507829903153204,
  "validation": {
    "risk_thermometer": "高烧威胁",
    "ath_drawdown": 39.01978767905155,
    "ath_price": 124797.86,
    "etf_accelerator": "钝化",
    "etf_net_flow": 0.0,
    "etf_aum": 83830573952.0,
    "etf_flow_14d_sum": 2171800000.0,
    "etf_flow_pos_ratio": 0.6,
    "etf_flow_recent_avg": 80071428.57142857,
    "etf_flow_prev_avg": 230185714.2857143,
    "etf_flow_trend": "down",
    "etf_aum_trend": "up"
  },
  "metadata": {
    "btc_price": 76102.0,
    "ma50": 71959.7398,
    "ma200": 84620.73555,
    "ma50_slope": 0.24462341529611908,
    "ma200_slope": -0.26033389286007624,
    "total_market_cap": 2630640983661.121,
    "stablecoin_market_cap": 273916224926.88324,
    "stablecoin_ratio": 10.412527845045126,
    "stablecoin_change": 39237374344.96719,
    "stablecoin_ratio_change": 2.412527845045126,
    "stablecoin_ratio_gap": null,
    "stablecoin_slope": 0.31883711193256836,
    "total_slope": 0.31883711193256836,
    "ath_drawdown": 39.01978767905155
  }
}